[
  {
    "Datetime": "1713124592",
    "DstMetadata": "{\"DwgVersion\":\"AutoCAD 2018\"}",
    "DstPath": "C:\\Academics\\sem4\\MDI\\AutocadLab\\Labtask4.dwg",
    "DstType": "dwg",
    "DstVersionId": "{C588C928-D4A7-5246-A0F9-C0FA02BD48BC}",
    "Op": "SAVE",
    "Product": "AutoCAD 2024",
    "SrcMetadata": "{\"DwgVersion\":\"AutoCAD 2018\",\"dbmod\":31}",
    "SrcPath": "C:\\Academics\\sem4\\MDI\\AutocadLab\\Labtask4.dwg",
    "SrcType": "dwg",
    "SrcVersionId": "{CFF1F71D-41C7-194E-844A-7D303BABDE6D}",
    "Username": "Utkarsh ghore"
  }
]